dsud/__init__.py
dsud/admin.py
dsud/apps.py
dsud/decorators.py
dsud/middleware.py
dsud/routers.py
dsud/signals.py
dsud/test_runner.py
dsud/urls.py
dsud/utils.py
dsud/management/__init__.py
dsud/management/commands/__init__.py
dsud/management/commands/create_user_db.py
dsud/management/commands/migrate_user_dbs.py
dsud/templates/dsud/admin/base_site.html
dsud/templatetags/__init__.py
dsud/templatetags/user_filters.py
dsud/tests/__init__.py
dsud/tests/settings.py
dsud/tests/test_admin.py
dsud/tests/test_db_utils.py
dsud/tests/urls.py
django_sqlite_user_db-0.1.2.dist-info/LICENSE.txt
django_sqlite_user_db-0.1.2.dist-info/METADATA
django_sqlite_user_db-0.1.2.dist-info/WHEEL
django_sqlite_user_db-0.1.2.dist-info/top_level.txt
django_sqlite_user_db-0.1.2.dist-info/RECORD
