Metadata-Version: 2.1
Name: django-sqlite-user-db
Version: 0.1.2
Summary: A Django package to create and manage user-specific SQLite databases.
Home-page: https://github.com/MessyComposer/django-sqlite-user-db
Author: Messy Composer
Author-email: 
License: MIT
Classifier: Programming Language :: Python :: 3
Classifier: Framework :: Django
Classifier: License :: OSI Approved :: MIT License
Classifier: Operating System :: OS Independent
Requires-Python: >=3.8
License-File: LICENSE.txt
Requires-Dist: Django >=4.2.16
Requires-Dist: asgiref >=3.8.1
